auto_mock.py
python_auto_mock-0.1.1.dist-info/METADATA
python_auto_mock-0.1.1.dist-info/RECORD
python_auto_mock-0.1.1.dist-info/WHEEL
python_auto_mock-0.1.1.dist-info/top_level.txt
python_auto_mock-0.1.1.dist-info/DESCRIPTION.rst
python_auto_mock-0.1.1.dist-info/metadata.json
